django_user_hash-1.0.2.dist-info/DESCRIPTION.rst
django_user_hash-1.0.2.dist-info/METADATA
django_user_hash-1.0.2.dist-info/RECORD
django_user_hash-1.0.2.dist-info/WHEEL
django_user_hash-1.0.2.dist-info/metadata.json
django_user_hash-1.0.2.dist-info/top_level.txt
user_hash/__init__.py
user_hash/__version__.py
user_hash/admin.py
user_hash/models.py
user_hash/management/__init__.py
user_hash/management/commands/__init__.py
user_hash/management/commands/userhash_cleanup.py
user_hash/migrations/0001_initial.py
user_hash/migrations/__init__.py
